simple_flask_blueprint
