Metadata-Version: 1.0
Name: SimpleFlaskBlueprint
Version: 0.1.1
Summary: Simple Flask blueprint.
Home-page: http://pypi.python.org/pypi/SimpleFlaskBlueprint/
Author: Guido Barbaglia
Author-email: guido.barbaglia@gmail.com
License: LICENSE.txt
Platform: UNKNOWN
